insult_error.py
insult_error-0.3.1.dist-info/LICENSE
insult_error-0.3.1.dist-info/METADATA
insult_error-0.3.1.dist-info/WHEEL
insult_error-0.3.1.dist-info/top_level.txt
insult_error-0.3.1.dist-info/RECORD
