Metadata-Version: 2.1
Name: insult-error
Version: 0.3.1
Summary: Intentionally insulting exceptions
Home-page: https://github.com/keithfma/insult_error
Author: Keith Ma
Author-email: itsallnans@gmail.com
License: UNKNOWN
Platform: UNKNOWN
Classifier: License :: OSI Approved :: MIT License
